config_box/__init__.py
config_box/exception.py
config_box/main.py
config_box-0.2.1600119743.dist-info/METADATA
config_box-0.2.1600119743.dist-info/WHEEL
config_box-0.2.1600119743.dist-info/top_level.txt
config_box-0.2.1600119743.dist-info/RECORD
